httpie_svb_auth.py
httpie_svb_auth-1.0.4.dist-info/DESCRIPTION.rst
httpie_svb_auth-1.0.4.dist-info/METADATA
httpie_svb_auth-1.0.4.dist-info/RECORD
httpie_svb_auth-1.0.4.dist-info/WHEEL
httpie_svb_auth-1.0.4.dist-info/entry_points.txt
httpie_svb_auth-1.0.4.dist-info/metadata.json
httpie_svb_auth-1.0.4.dist-info/top_level.txt
httpie_svb_auth-1.0.4.dist-info/zip-safe
