Metadata-Version: 2.0
Name: httpie-svb-auth
Version: 1.0.4
Summary: SVB API auth plugin for HTTPie.
Home-page: https://github.com/svb/httpie-svb-auth
Author: Jim Brusstar
Author-email: jim.brusstar@gmail.com
License: MIT
Download-URL: https://github.com/svb/httpie-svb-auth
Keywords: httpie,svb
Platform: UNKNOWN
Classifier: Development Status :: 5 - Production/Stable
Classifier: Environment :: Plugins
Classifier: Intended Audience :: Developers
Classifier: License :: OSI Approved :: MIT License
Classifier: Operating System :: OS Independent
Classifier: Programming Language :: Python
Classifier: Topic :: Internet :: WWW/HTTP
Classifier: Topic :: Utilities
Requires-Dist: httpie (>=0.7.0)
